LICENSE.md
MANIFEST.in
README.rst
requirements.txt
setup.py
antgo/__init__.py
antgo/command.py
antgo/config.py
antgo/config.xml
antgo/context.py
antgo/help.py
antgo/interactcontext.py
antgo/main.py
antgo/main_backup.py
antgo/version.py
antgo.egg-info/PKG-INFO
antgo.egg-info/SOURCES.txt
antgo.egg-info/dependency_links.txt
antgo.egg-info/entry_points.txt
antgo.egg-info/not-zip-safe
antgo.egg-info/top_level.txt
antgo/ant/__init__.py
antgo/ant/activelearning.py
antgo/ant/activelearning_api.py
antgo/ant/activelearning_v2.py
antgo/ant/analysis.py
antgo/ant/base.py
antgo/ant/batch.py
antgo/ant/browser.py
antgo/ant/challenge.py
antgo/ant/client.py
antgo/ant/debug.py
antgo/ant/demo.py
antgo/ant/download.py
antgo/ant/ensemble.py
antgo/ant/environment.py
antgo/ant/flags.py
antgo/ant/train.py
antgo/ant/utils.py
antgo/ant/watch.py
antgo/crowdsource/__init__.py
antgo/crowdsource/activelearning_server.py
antgo/crowdsource/base_server.py
antgo/crowdsource/batch_server.py
antgo/crowdsource/browser_server.py
antgo/crowdsource/crowdsource_server.py
antgo/crowdsource/demo_server.py
antgo/crowdsource/ensemble_server.py
antgo/crowdsource/label_server.py
antgo/crowdsource/utils.py
antgo/crowdsource/watch_server.py
antgo/cutils/maskApi.c
antgo/cutils/maskApi.h
antgo/dataflow/__init__.py
antgo/dataflow/basic.py
antgo/dataflow/common.py
antgo/dataflow/core.py
antgo/dataflow/datasetio.py
antgo/dataflow/recorder.py
antgo/dataflow/vis.py
antgo/dataflow/dataset/__init__.py
antgo/dataflow/dataset/ade20k.py
antgo/dataflow/dataset/celeba.py
antgo/dataflow/dataset/cifar.py
antgo/dataflow/dataset/cityscape.py
antgo/dataflow/dataset/clsdataset.py
antgo/dataflow/dataset/coco2017.py
antgo/dataflow/dataset/cusdomcls.py
antgo/dataflow/dataset/dataset.py
antgo/dataflow/dataset/empty_dataset.py
antgo/dataflow/dataset/fashionai_attribute.py
antgo/dataflow/dataset/fashionai_landmark.py
antgo/dataflow/dataset/flic.py
antgo/dataflow/dataset/horse2zebra.py
antgo/dataflow/dataset/imagenet.py
antgo/dataflow/dataset/interhand26M.py
antgo/dataflow/dataset/iphone2dslr.py
antgo/dataflow/dataset/lfw.py
antgo/dataflow/dataset/lip.py
antgo/dataflow/dataset/lsp.py
