Metadata-Version: 2.1
Name: antgo
Version: 0.1.24
Summary: machine learning experiment platform
Home-page: https://github.com/jianzfb/antgo
Author: jian
Author-email: jian@mltalker.com
License-File: LICENSE.md
